pyzure_docdb/__init__.py
pyzure_docdb/documentdb.py
pyzure_documentdb-0.1.0.dev3.dist-info/DESCRIPTION.rst
pyzure_documentdb-0.1.0.dev3.dist-info/METADATA
pyzure_documentdb-0.1.0.dev3.dist-info/RECORD
pyzure_documentdb-0.1.0.dev3.dist-info/WHEEL
pyzure_documentdb-0.1.0.dev3.dist-info/metadata.json
pyzure_documentdb-0.1.0.dev3.dist-info/top_level.txt
